LICENSE
MANIFEST.in
README.md
requirements-base.txt
requirements-dev.txt
requirements-test.txt
setup.py
pipsqueak/__init__.py
pipsqueak/exceptions.py
pipsqueak/main.py
pipsqueak/options.py
pipsqueak.egg-info/PKG-INFO
pipsqueak.egg-info/SOURCES.txt
pipsqueak.egg-info/dependency_links.txt
pipsqueak.egg-info/entry_points.txt
pipsqueak.egg-info/not-zip-safe
pipsqueak.egg-info/requires.txt
pipsqueak.egg-info/top_level.txt
pipsqueak/pip/__init__.py
pipsqueak/pip/compat.py
pipsqueak/pip/freeze.py
pipsqueak/pip/index.py
pipsqueak/pip/link.py
pipsqueak/pip/req_install.py
pipsqueak/pip/util.py
pipsqueak/pip/wheel.py
pipsqueak/pip/vcs/__init__.py
pipsqueak/pip/vcs/bazaar.py
pipsqueak/pip/vcs/git.py
pipsqueak/pip/vcs/mercurial.py
pipsqueak/pip/vcs/subversion.py