Metadata-Version: 1.1
Name: pipsqueak
Version: 0.0.14
Summary: Parse and compare pip requirements
Home-page: http://github.com/svrana/pipsqueak
Author: Shaw Vrana
Author-email: shaw@vranix.com
License: MIT
Platform: UNKNOWN
Classifier: License :: OSI Approved :: MIT License
Classifier: Development Status :: 3 - Alpha
Classifier: Intended Audience :: Developers
Classifier: Programming Language :: Python :: 2.7
Classifier: Topic :: Software Development :: Libraries :: Python Modules
